pytheus/__init__.py
pytheus/analyzer.py
pytheus/bla.py
pytheus/cli.py
pytheus/fancy_classes.py
pytheus/graphplot.py
pytheus/graphplot_lts.py
pytheus/help_functions.py
pytheus/leiwand.py
pytheus/lossfunctions.py
pytheus/main.py
pytheus/optimizer.py
pytheus/optimizer_mario.py
pytheus/saver.py
pytheus/theseus.py
pytheus/custom_loss/__init__.py
pytheus/custom_loss/assembly_index.py
pytheus/graphs/AssemblyIndex/.DS_Store
pytheus/graphs/AssemblyIndex/assembly4/config_assembly4.json
pytheus/graphs/AssemblyIndex/assembly4/plot_assembly4.json
pytheus/graphs/AssemblyIndex/assembly6/config_assembly6.json
pytheus/graphs/AssemblyIndex/assembly6/plot_assembly6.json
pytheus/graphs/Communication/2pES_3d/config_2pES_3d.json
pytheus/graphs/Communication/2pES_3d/graph_2pES_3d.aux
pytheus/graphs/Communication/2pES_3d/graph_2pES_3d.pdf
pytheus/graphs/Communication/2pES_3d/graph_2pES_3d.tex
pytheus/graphs/Communication/2pES_3d/original_2pES_3d_clean-16-9-0-0.1000_0.0000.json
pytheus/graphs/Communication/2pES_3d/plot_2pES_3d_clean-16-9-0.1000_0.0000.json
pytheus/graphs/Communication/3pES/config_3pES.json
pytheus/graphs/Communication/3pES/graph_3pES.aux
pytheus/graphs/Communication/3pES/graph_3pES.pdf
pytheus/graphs/Communication/3pES/graph_3pES.tex
pytheus/graphs/Communication/3pES/plot_3pES_clean-18-16-0.1111_0.0000.json
pytheus/graphs/Communication/ES3d_sp/config_ES3d_sp.json
pytheus/graphs/Communication/ES3d_sp/graph_ES3d_sp.aux
pytheus/graphs/Communication/ES3d_sp/graph_ES3d_sp.pdf
pytheus/graphs/Communication/ES3d_sp/graph_ES3d_sp.tex
pytheus/graphs/Communication/ES3d_sp/plot_ES3d_sp_clean-18-14-0.0769_0.0000.json
pytheus/graphs/Communication/ES_246/config_ES_246.json
pytheus/graphs/Communication/ES_246/graph_ES_246.aux
pytheus/graphs/Communication/ES_246/graph_ES_246.pdf
pytheus/graphs/Communication/ES_246/graph_ES_246.tex
pytheus/graphs/Communication/ES_246/original_clean-12-6-0.2000_0.0000.json
pytheus/graphs/Communication/ES_246/plot_clean-12-6-0.2000_0.0000.json
pytheusQ-1.2.21.dist-info/LICENSE
pytheusQ-1.2.21.dist-info/METADATA
pytheusQ-1.2.21.dist-info/WHEEL
pytheusQ-1.2.21.dist-info/entry_points.txt
pytheusQ-1.2.21.dist-info/top_level.txt
pytheusQ-1.2.21.dist-info/RECORD
