Metadata-Version: 2.1
Name: pytheusQ
Version: 1.2.21
Summary: PyTheus, a highly-efficient inverse-design algorithm for quantum optical experiments
Home-page: https://github.com/artificial-scientist-lab/Pytheus
Author: artificial-scientist-lab
Author-email: cruizgo@proton.me, soeren.arlt@mpl.mpg.de, mario.krenn@mpl.mpg.de
License: MIT
Platform: ALL
Classifier: Operating System :: OS Independent
Classifier: Programming Language :: Python :: 3
Requires-Python: >=3.8
Requires-Dist: sphinx
Requires-Dist: numpy
Requires-Dist: scipy
Requires-Dist: matplotlib
Requires-Dist: termcolor
Requires-Dist: Click
